{
  "2025-07-20": [
    {
      "videoId": "O5zmjhxmE9E",
      "teamName": "MOTIV",
      "rawLikes": 103200,
      "rawDislikes": 900,
      "dateCreated": "2025-07-20 00:29:48",
      "collectedAt": "2025-07-20 01:00:01"
    },
    {
      "videoId": "O5zmjhxmE9E",
      "teamName": "MOTIV",
      "rawLikes": 103800,
      "rawDislikes": 900,
      "dateCreated": "2025-07-20 01:05:48",
      "collectedAt": "2025-07-20 01:30:01"
    },
    {
      "videoId": "O5zmjhxmE9E",
      "teamName": "MOTIV",
      "rawLikes": 104400,
      "rawDislikes": 900,
      "dateCreated": "2025-07-20 02:26:11",
      "collectedAt": "2025-07-20 02:30:01"
    },
    {
      "videoId": "O5zmjhxmE9E",
      "teamName": "MOTIV",
      "rawLikes": 104600,
      "rawDislikes": 900,
      "dateCreated": "2025-07-20 03:08:50",
      "collectedAt": "2025-07-20 03:30:01"
    },
    {
      "videoId": "O5zmjhxmE9E",
      "teamName": "MOTIV",
      "rawLikes": 104800,
      "rawDislikes": 900,
      "dateCreated": "2025-07-20 04:13:51",
      "collectedAt": "2025-07-20 04:30:01"
    },
    {
      "videoId": "O5zmjhxmE9E",
      "teamName": "MOTIV",
      "rawLikes": 104800,
      "rawDislikes": 900,
      "dateCreated": "2025-07-20 05:00:00",
      "collectedAt": "2025-07-20 05:30:01"
    },
    {
      "videoId": "O5zmjhxmE9E",
      "teamName": "MOTIV",
      "rawLikes": 105000,
      "rawDislikes": 900,
      "dateCreated": "2025-07-20 06:30:01",
      "collectedAt": "2025-07-20 07:00:01"
    },
    {
      "videoId": "O5zmjhxmE9E",
      "teamName": "MOTIV",
      "rawLikes": 105000,
      "rawDislikes": 900,
      "dateCreated": "2025-07-20 07:30:00",
      "collectedAt": "2025-07-20 08:00:01"
    },
    {
      "videoId": "O5zmjhxmE9E",
      "teamName": "MOTIV",
      "rawLikes": 105200,
      "rawDislikes": 900,
      "dateCreated": "2025-07-20 08:08:48",
      "collectedAt": "2025-07-20 08:30:01"
    },
    {
      "videoId": "O5zmjhxmE9E",
      "teamName": "MOTIV",
      "rawLikes": 105800,
      "rawDislikes": 900,
      "dateCreated": "2025-07-20 09:02:31",
      "collectedAt": "2025-07-20 09:30:01"
    },
    {
      "videoId": "O5zmjhxmE9E",
      "teamName": "MOTIV",
      "rawLikes": 106000,
      "rawDislikes": 900,
      "dateCreated": "2025-07-20 10:21:04",
      "collectedAt": "2025-07-20 10:30:01"
    },
    {
      "videoId": "O5zmjhxmE9E",
      "teamName": "MOTIV",
      "rawLikes": 106200,
      "rawDislikes": 900,
      "dateCreated": "2025-07-20 11:57:11",
      "collectedAt": "2025-07-20 12:00:01"
    },
    {
      "videoId": "O5zmjhxmE9E",
      "teamName": "MOTIV",
      "rawLikes": 106400,
      "rawDislikes": 900,
      "dateCreated": "2025-07-20 12:30:00",
      "collectedAt": "2025-07-20 13:00:01"
    },
    {
      "videoId": "O5zmjhxmE9E",
      "teamName": "MOTIV",
      "rawLikes": 106400,
      "rawDislikes": 900,
      "dateCreated": "2025-07-20 13:03:15",
      "collectedAt": "2025-07-20 13:30:01"
    },
    {
      "videoId": "O5zmjhxmE9E",
      "teamName": "MOTIV",
      "rawLikes": 106800,
      "rawDislikes": 900,
      "dateCreated": "2025-07-20 14:28:55",
      "collectedAt": "2025-07-20 14:30:01"
    },
    {
      "videoId": "O5zmjhxmE9E",
      "teamName": "MOTIV",
      "rawLikes": 107200,
      "rawDislikes": 900,
      "dateCreated": "2025-07-20 15:30:30",
      "collectedAt": "2025-07-20 16:00:01"
    },
    {
      "videoId": "O5zmjhxmE9E",
      "teamName": "MOTIV",
      "rawLikes": 107600,
      "rawDislikes": 900,
      "dateCreated": "2025-07-20 16:24:17",
      "collectedAt": "2025-07-20 16:30:01"
    },
    {
      "videoId": "O5zmjhxmE9E",
      "teamName": "MOTIV",
      "rawLikes": 108400,
      "rawDislikes": 900,
      "dateCreated": "2025-07-20 17:47:50",
      "collectedAt": "2025-07-20 18:00:01"
    },
    {
      "videoId": "O5zmjhxmE9E",
      "teamName": "MOTIV",
      "rawLikes": 108400,
      "rawDislikes": 900,
      "dateCreated": "2025-07-20 18:12:28",
      "collectedAt": "2025-07-20 18:14:01"
    }
  ],
  "2025-07-19": [
    {
      "videoId": "O5zmjhxmE9E",
      "teamName": "MOTIV",
      "rawLikes": 95200,
      "rawDislikes": 800,
      "dateCreated": "2025-07-19 00:01:56",
      "collectedAt": "2025-07-19 00:30:01"
    },
    {
      "videoId": "O5zmjhxmE9E",
      "teamName": "MOTIV",
      "rawLikes": 95400,
      "rawDislikes": 800,
      "dateCreated": "2025-07-19 01:15:00",
      "collectedAt": "2025-07-19 01:30:01"
    },
    {
      "videoId": "O5zmjhxmE9E",
      "teamName": "MOTIV",
      "rawLikes": 95800,
      "rawDislikes": 800,
      "dateCreated": "2025-07-19 02:24:35",
      "collectedAt": "2025-07-19 02:30:01"
    },
    {
      "videoId": "O5zmjhxmE9E",
      "teamName": "MOTIV",
      "rawLikes": 97000,
      "rawDislikes": 800,
      "dateCreated": "2025-07-19 03:22:37",
      "collectedAt": "2025-07-19 03:30:01"
    },
    {
      "videoId": "O5zmjhxmE9E",
      "teamName": "MOTIV",
      "rawLikes": 97200,
      "rawDislikes": 800,
      "dateCreated": "2025-07-19 04:07:09",
      "collectedAt": "2025-07-19 04:30:01"
    },
    {
      "videoId": "O5zmjhxmE9E",
      "teamName": "MOTIV",
      "rawLikes": 97600,
      "rawDislikes": 800,
      "dateCreated": "2025-07-19 05:32:14",
      "collectedAt": "2025-07-19 06:00:01"
    },
    {
      "videoId": "O5zmjhxmE9E",
      "teamName": "MOTIV",
      "rawLikes": 98000,
      "rawDislikes": 800,
      "dateCreated": "2025-07-19 06:56:47",
      "collectedAt": "2025-07-19 07:00:01"
    },
    {
      "videoId": "O5zmjhxmE9E",
      "teamName": "MOTIV",
      "rawLikes": 98200,
      "rawDislikes": 800,
      "dateCreated": "2025-07-19 07:30:44",
      "collectedAt": "2025-07-19 08:00:01"
    },
    {
      "videoId": "O5zmjhxmE9E",
      "teamName": "MOTIV",
      "rawLikes": 98200,
      "rawDislikes": 800,
      "dateCreated": "2025-07-19 08:04:00",
      "collectedAt": "2025-07-19 08:30:01"
    },
    {
      "videoId": "O5zmjhxmE9E",
      "teamName": "MOTIV",
      "rawLikes": 98200,
      "rawDislikes": 800,
      "dateCreated": "2025-07-19 09:00:01",
      "collectedAt": "2025-07-19 09:30:00"
    },
    {
      "videoId": "O5zmjhxmE9E",
      "teamName": "MOTIV",
      "rawLikes": 98200,
      "rawDislikes": 800,
      "dateCreated": "2025-07-19 10:17:56",
      "collectedAt": "2025-07-19 10:30:01"
    },
    {
      "videoId": "O5zmjhxmE9E",
      "teamName": "MOTIV",
      "rawLikes": 99000,
      "rawDislikes": 800,
      "dateCreated": "2025-07-19 11:22:16",
      "collectedAt": "2025-07-19 11:30:01"
    },
    {
      "videoId": "O5zmjhxmE9E",
      "teamName": "MOTIV",
      "rawLikes": 99600,
      "rawDislikes": 800,
      "dateCreated": "2025-07-19 12:30:01",
      "collectedAt": "2025-07-19 13:00:01"
    },
    {
      "videoId": "O5zmjhxmE9E",
      "teamName": "MOTIV",
      "rawLikes": 99800,
      "rawDislikes": 800,
      "dateCreated": "2025-07-19 13:19:13",
      "collectedAt": "2025-07-19 13:30:01"
    },
    {
      "videoId": "O5zmjhxmE9E",
      "teamName": "MOTIV",
      "rawLikes": 100000,
      "rawDislikes": 800,
      "dateCreated": "2025-07-19 14:48:53",
      "collectedAt": "2025-07-19 15:00:01"
    },
    {
      "videoId": "O5zmjhxmE9E",
      "teamName": "MOTIV",
      "rawLikes": 100000,
      "rawDislikes": 800,
      "dateCreated": "2025-07-19 15:07:39",
      "collectedAt": "2025-07-19 15:30:01"
    },
    {
      "videoId": "O5zmjhxmE9E",
      "teamName": "MOTIV",
      "rawLikes": 100200,
      "rawDislikes": 800,
      "dateCreated": "2025-07-19 16:12:34",
      "collectedAt": "2025-07-19 16:30:01"
    },
    {
      "videoId": "O5zmjhxmE9E",
      "teamName": "MOTIV",
      "rawLikes": 100200,
      "rawDislikes": 800,
      "dateCreated": "2025-07-19 17:11:33",
      "collectedAt": "2025-07-19 17:30:01"
    },
    {
      "videoId": "O5zmjhxmE9E",
      "teamName": "MOTIV",
      "rawLikes": 100400,
      "rawDislikes": 800,
      "dateCreated": "2025-07-19 18:19:19",
      "collectedAt": "2025-07-19 18:30:01"
    },
    {
      "videoId": "O5zmjhxmE9E",
      "teamName": "MOTIV",
      "rawLikes": 100600,
      "rawDislikes": 800,
      "dateCreated": "2025-07-19 19:12:35",
      "collectedAt": "2025-07-19 19:30:01"
    },
    {
      "videoId": "O5zmjhxmE9E",
      "teamName": "MOTIV",
      "rawLikes": 101000,
      "rawDislikes": 800,
      "dateCreated": "2025-07-19 20:16:15",
      "collectedAt": "2025-07-19 20:30:01"
    },
    {
      "videoId": "O5zmjhxmE9E",
      "teamName": "MOTIV",
      "rawLikes": 101400,
      "rawDislikes": 800,
      "dateCreated": "2025-07-19 21:22:41",
      "collectedAt": "2025-07-19 21:30:01"
    },
    {
      "videoId": "O5zmjhxmE9E",
      "teamName": "MOTIV",
      "rawLikes": 101800,
      "rawDislikes": 800,
      "dateCreated": "2025-07-19 22:00:01",
      "collectedAt": "2025-07-19 22:30:00"
    },
    {
      "videoId": "O5zmjhxmE9E",
      "teamName": "MOTIV",
      "rawLikes": 102200,
      "rawDislikes": 800,
      "dateCreated": "2025-07-19 23:03:06",
      "collectedAt": "2025-07-19 23:30:01"
    }
  ],
  "2025-07-18": [
    {
      "videoId": "O5zmjhxmE9E",
      "teamName": "MOTIV",
      "rawLikes": 86400,
      "rawDislikes": 600,
      "dateCreated": "2025-07-18 00:21:25",
      "collectedAt": "2025-07-18 00:30:01"
    },
    {
      "videoId": "O5zmjhxmE9E",
      "teamName": "MOTIV",
      "rawLikes": 87200,
      "rawDislikes": 600,
      "dateCreated": "2025-07-18 01:20:23",
      "collectedAt": "2025-07-18 01:30:01"
    },
    {
      "videoId": "O5zmjhxmE9E",
      "teamName": "MOTIV",
      "rawLikes": 87600,
      "rawDislikes": 600,
      "dateCreated": "2025-07-18 02:27:15",
      "collectedAt": "2025-07-18 02:30:01"
    },
    {
      "videoId": "O5zmjhxmE9E",
      "teamName": "MOTIV",
      "rawLikes": 88200,
      "rawDislikes": 600,
      "dateCreated": "2025-07-18 03:30:01",
      "collectedAt": "2025-07-18 04:00:01"
    },
    {
      "videoId": "O5zmjhxmE9E",
      "teamName": "MOTIV",
      "rawLikes": 88200,
      "rawDislikes": 600,
      "dateCreated": "2025-07-18 04:09:30",
      "collectedAt": "2025-07-18 04:30:01"
    },
    {
      "videoId": "O5zmjhxmE9E",
      "teamName": "MOTIV",
      "rawLikes": 88400,
      "rawDislikes": 600,
      "dateCreated": "2025-07-18 05:14:11",
      "collectedAt": "2025-07-18 05:30:00"
    },
    {
      "videoId": "O5zmjhxmE9E",
      "teamName": "MOTIV",
      "rawLikes": 88600,
      "rawDislikes": 600,
      "dateCreated": "2025-07-18 06:00:01",
      "collectedAt": "2025-07-18 06:30:01"
    },
    {
      "videoId": "O5zmjhxmE9E",
      "teamName": "MOTIV",
      "rawLikes": 89400,
      "rawDislikes": 600,
      "dateCreated": "2025-07-18 07:53:16",
      "collectedAt": "2025-07-18 08:00:01"
    },
    {
      "videoId": "O5zmjhxmE9E",
      "teamName": "MOTIV",
      "rawLikes": 89400,
      "rawDislikes": 600,
      "dateCreated": "2025-07-18 08:24:03",
      "collectedAt": "2025-07-18 08:30:01"
    },
    {
      "videoId": "O5zmjhxmE9E",
      "teamName": "MOTIV",
      "rawLikes": 90200,
      "rawDislikes": 600,
      "dateCreated": "2025-07-18 09:12:27",
      "collectedAt": "2025-07-18 09:30:01"
    },
    {
      "videoId": "O5zmjhxmE9E",
      "teamName": "MOTIV",
      "rawLikes": 91000,
      "rawDislikes": 600,
      "dateCreated": "2025-07-18 10:11:44",
      "collectedAt": "2025-07-18 10:30:01"
    },
    {
      "videoId": "O5zmjhxmE9E",
      "teamName": "MOTIV",
      "rawLikes": 91200,
      "rawDislikes": 700,
      "dateCreated": "2025-07-18 11:09:06",
      "collectedAt": "2025-07-18 11:30:01"
    },
    {
      "videoId": "O5zmjhxmE9E",
      "teamName": "MOTIV",
      "rawLikes": 91200,
      "rawDislikes": 700,
      "dateCreated": "2025-07-18 12:16:40",
      "collectedAt": "2025-07-18 12:30:01"
    },
    {
      "videoId": "O5zmjhxmE9E",
      "teamName": "MOTIV",
      "rawLikes": 91200,
      "rawDislikes": 700,
      "dateCreated": "2025-07-18 13:29:20",
      "collectedAt": "2025-07-18 13:30:01"
    },
    {
      "videoId": "O5zmjhxmE9E",
      "teamName": "MOTIV",
      "rawLikes": 91800,
      "rawDislikes": 700,
      "dateCreated": "2025-07-18 14:00:01",
      "collectedAt": "2025-07-18 14:30:01"
    },
    {
      "videoId": "O5zmjhxmE9E",
      "teamName": "MOTIV",
      "rawLikes": 92000,
      "rawDislikes": 800,
      "dateCreated": "2025-07-18 15:18:36",
      "collectedAt": "2025-07-18 15:30:01"
    },
    {
      "videoId": "O5zmjhxmE9E",
      "teamName": "MOTIV",
      "rawLikes": 92400,
      "rawDislikes": 800,
      "dateCreated": "2025-07-18 16:22:13",
      "collectedAt": "2025-07-18 16:30:01"
    },
    {
      "videoId": "O5zmjhxmE9E",
      "teamName": "MOTIV",
      "rawLikes": 92600,
      "rawDislikes": 800,
      "dateCreated": "2025-07-18 17:03:44",
      "collectedAt": "2025-07-18 17:30:01"
    },
    {
      "videoId": "O5zmjhxmE9E",
      "teamName": "MOTIV",
      "rawLikes": 93200,
      "rawDislikes": 800,
      "dateCreated": "2025-07-18 18:26:23",
      "collectedAt": "2025-07-18 18:30:01"
    },
    {
      "videoId": "O5zmjhxmE9E",
      "teamName": "MOTIV",
      "rawLikes": 93600,
      "rawDislikes": 800,
      "dateCreated": "2025-07-18 19:23:15",
      "collectedAt": "2025-07-18 19:30:01"
    },
    {
      "videoId": "O5zmjhxmE9E",
      "teamName": "MOTIV",
      "rawLikes": 94200,
      "rawDislikes": 800,
      "dateCreated": "2025-07-18 20:16:59",
      "collectedAt": "2025-07-18 20:30:01"
    },
    {
      "videoId": "O5zmjhxmE9E",
      "teamName": "MOTIV",
      "rawLikes": 94400,
      "rawDislikes": 800,
      "dateCreated": "2025-07-18 21:20:48",
      "collectedAt": "2025-07-18 21:30:01"
    },
    {
      "videoId": "O5zmjhxmE9E",
      "teamName": "MOTIV",
      "rawLikes": 94800,
      "rawDislikes": 800,
      "dateCreated": "2025-07-18 22:14:04",
      "collectedAt": "2025-07-18 22:30:01"
    },
    {
      "videoId": "O5zmjhxmE9E",
      "teamName": "MOTIV",
      "rawLikes": 94600,
      "rawDislikes": 800,
      "dateCreated": "2025-07-18 23:07:44",
      "collectedAt": "2025-07-18 23:30:00"
    }
  ],
  "2025-07-17": [
    {
      "videoId": "O5zmjhxmE9E",
      "teamName": "MOTIV",
      "rawLikes": 71600,
      "rawDislikes": 600,
      "dateCreated": "2025-07-17 00:29:09",
      "collectedAt": "2025-07-17 00:30:01"
    },
    {
      "videoId": "O5zmjhxmE9E",
      "teamName": "MOTIV",
      "rawLikes": 73000,
      "rawDislikes": 600,
      "dateCreated": "2025-07-17 01:23:25",
      "collectedAt": "2025-07-17 01:30:01"
    },
    {
      "videoId": "O5zmjhxmE9E",
      "teamName": "MOTIV",
      "rawLikes": 73800,
      "rawDislikes": 600,
      "dateCreated": "2025-07-17 02:03:10",
      "collectedAt": "2025-07-17 02:30:01"
    },
    {
      "videoId": "O5zmjhxmE9E",
      "teamName": "MOTIV",
      "rawLikes": 75200,
      "rawDislikes": 600,
      "dateCreated": "2025-07-17 03:00:01",
      "collectedAt": "2025-07-17 03:30:01"
    },
    {
      "videoId": "O5zmjhxmE9E",
      "teamName": "MOTIV",
      "rawLikes": 75800,
      "rawDislikes": 600,
      "dateCreated": "2025-07-17 04:23:29",
      "collectedAt": "2025-07-17 04:30:01"
    },
    {
      "videoId": "O5zmjhxmE9E",
      "teamName": "MOTIV",
      "rawLikes": 76200,
      "rawDislikes": 600,
      "dateCreated": "2025-07-17 05:15:38",
      "collectedAt": "2025-07-17 05:30:00"
    },
    {
      "videoId": "O5zmjhxmE9E",
      "teamName": "MOTIV",
      "rawLikes": 76400,
      "rawDislikes": 600,
      "dateCreated": "2025-07-17 06:00:49",
      "collectedAt": "2025-07-17 06:30:01"
    },
    {
      "videoId": "O5zmjhxmE9E",
      "teamName": "MOTIV",
      "rawLikes": 76800,
      "rawDislikes": 600,
      "dateCreated": "2025-07-17 07:46:25",
      "collectedAt": "2025-07-17 08:00:01"
    },
    {
      "videoId": "O5zmjhxmE9E",
      "teamName": "MOTIV",
      "rawLikes": 77400,
      "rawDislikes": 600,
      "dateCreated": "2025-07-17 08:13:26",
      "collectedAt": "2025-07-17 08:30:01"
    },
    {
      "videoId": "O5zmjhxmE9E",
      "teamName": "MOTIV",
      "rawLikes": 78600,
      "rawDislikes": 600,
      "dateCreated": "2025-07-17 09:10:02",
      "collectedAt": "2025-07-17 09:30:01"
    },
    {
      "videoId": "O5zmjhxmE9E",
      "teamName": "MOTIV",
      "rawLikes": 79000,
      "rawDislikes": 600,
      "dateCreated": "2025-07-17 10:14:15",
      "collectedAt": "2025-07-17 10:30:01"
    },
    {
      "videoId": "O5zmjhxmE9E",
      "teamName": "MOTIV",
      "rawLikes": 79400,
      "rawDislikes": 600,
      "dateCreated": "2025-07-17 11:19:27",
      "collectedAt": "2025-07-17 11:30:01"
    },
    {
      "videoId": "O5zmjhxmE9E",
      "teamName": "MOTIV",
      "rawLikes": 80400,
      "rawDislikes": 600,
      "dateCreated": "2025-07-17 12:56:55",
      "collectedAt": "2025-07-17 13:00:01"
    },
    {
      "videoId": "O5zmjhxmE9E",
      "teamName": "MOTIV",
      "rawLikes": 80800,
      "rawDislikes": 600,
      "dateCreated": "2025-07-17 13:22:42",
      "collectedAt": "2025-07-17 13:30:01"
    },
    {
      "videoId": "O5zmjhxmE9E",
      "teamName": "MOTIV",
      "rawLikes": 81000,
      "rawDislikes": 600,
      "dateCreated": "2025-07-17 14:00:13",
      "collectedAt": "2025-07-17 14:30:01"
    },
    {
      "videoId": "O5zmjhxmE9E",
      "teamName": "MOTIV",
      "rawLikes": 81800,
      "rawDislikes": 600,
      "dateCreated": "2025-07-17 15:26:39",
      "collectedAt": "2025-07-17 15:30:00"
    },
    {
      "videoId": "O5zmjhxmE9E",
      "teamName": "MOTIV",
      "rawLikes": 82000,
      "rawDislikes": 600,
      "dateCreated": "2025-07-17 16:21:21",
      "collectedAt": "2025-07-17 16:30:01"
    },
    {
      "videoId": "O5zmjhxmE9E",
      "teamName": "MOTIV",
      "rawLikes": 82200,
      "rawDislikes": 600,
      "dateCreated": "2025-07-17 17:10:44",
      "collectedAt": "2025-07-17 17:30:01"
    },
    {
      "videoId": "O5zmjhxmE9E",
      "teamName": "MOTIV",
      "rawLikes": 82800,
      "rawDislikes": 600,
      "dateCreated": "2025-07-17 18:15:56",
      "collectedAt": "2025-07-17 18:30:01"
    },
    {
      "videoId": "O5zmjhxmE9E",
      "teamName": "MOTIV",
      "rawLikes": 83400,
      "rawDislikes": 600,
      "dateCreated": "2025-07-17 19:23:58",
      "collectedAt": "2025-07-17 19:30:01"
    },
    {
      "videoId": "O5zmjhxmE9E",
      "teamName": "MOTIV",
      "rawLikes": 83600,
      "rawDislikes": 600,
      "dateCreated": "2025-07-17 20:17:45",
      "collectedAt": "2025-07-17 20:30:01"
    },
    {
      "videoId": "O5zmjhxmE9E",
      "teamName": "MOTIV",
      "rawLikes": 84000,
      "rawDislikes": 600,
      "dateCreated": "2025-07-17 21:05:56",
      "collectedAt": "2025-07-17 21:30:01"
    },
    {
      "videoId": "O5zmjhxmE9E",
      "teamName": "MOTIV",
      "rawLikes": 84600,
      "rawDislikes": 600,
      "dateCreated": "2025-07-17 22:23:16",
      "collectedAt": "2025-07-17 22:30:01"
    },
    {
      "videoId": "O5zmjhxmE9E",
      "teamName": "MOTIV",
      "rawLikes": 85000,
      "rawDislikes": 600,
      "dateCreated": "2025-07-17 23:26:31",
      "collectedAt": "2025-07-17 23:30:01"
    }
  ],
  "2025-07-16": [
    {
      "videoId": "O5zmjhxmE9E",
      "teamName": "MOTIV",
      "rawLikes": 3600,
      "rawDislikes": 0,
      "dateCreated": "2025-07-16 01:02:27",
      "collectedAt": "2025-07-16 01:05:00"
    },
    {
      "videoId": "O5zmjhxmE9E",
      "teamName": "MOTIV",
      "rawLikes": 22200,
      "rawDislikes": 200,
      "dateCreated": "2025-07-16 02:25:27",
      "collectedAt": "2025-07-16 02:30:01"
    },
    {
      "videoId": "O5zmjhxmE9E",
      "teamName": "MOTIV",
      "rawLikes": 27000,
      "rawDislikes": 200,
      "dateCreated": "2025-07-16 03:22:44",
      "collectedAt": "2025-07-16 03:30:01"
    },
    {
      "videoId": "O5zmjhxmE9E",
      "teamName": "MOTIV",
      "rawLikes": 29400,
      "rawDislikes": 200,
      "dateCreated": "2025-07-16 04:25:26",
      "collectedAt": "2025-07-16 04:30:01"
    },
    {
      "videoId": "O5zmjhxmE9E",
      "teamName": "MOTIV",
      "rawLikes": 32000,
      "rawDislikes": 200,
      "dateCreated": "2025-07-16 05:22:14",
      "collectedAt": "2025-07-16 05:30:01"
    },
    {
      "videoId": "O5zmjhxmE9E",
      "teamName": "MOTIV",
      "rawLikes": 33800,
      "rawDislikes": 200,
      "dateCreated": "2025-07-16 06:28:26",
      "collectedAt": "2025-07-16 06:30:01"
    },
    {
      "videoId": "O5zmjhxmE9E",
      "teamName": "MOTIV",
      "rawLikes": 36400,
      "rawDislikes": 200,
      "dateCreated": "2025-07-16 07:27:37",
      "collectedAt": "2025-07-16 07:30:01"
    },
    {
      "videoId": "O5zmjhxmE9E",
      "teamName": "MOTIV",
      "rawLikes": 38800,
      "rawDislikes": 300,
      "dateCreated": "2025-07-16 08:24:03",
      "collectedAt": "2025-07-16 08:30:00"
    },
    {
      "videoId": "O5zmjhxmE9E",
      "teamName": "MOTIV",
      "rawLikes": 41800,
      "rawDislikes": 300,
      "dateCreated": "2025-07-16 09:16:23",
      "collectedAt": "2025-07-16 09:30:00"
    },
    {
      "videoId": "O5zmjhxmE9E",
      "teamName": "MOTIV",
      "rawLikes": 43200,
      "rawDislikes": 300,
      "dateCreated": "2025-07-16 10:28:26",
      "collectedAt": "2025-07-16 10:30:01"
    },
    {
      "videoId": "O5zmjhxmE9E",
      "teamName": "MOTIV",
      "rawLikes": 45400,
      "rawDislikes": 300,
      "dateCreated": "2025-07-16 11:22:31",
      "collectedAt": "2025-07-16 11:30:01"
    },
    {
      "videoId": "O5zmjhxmE9E",
      "teamName": "MOTIV",
      "rawLikes": 48600,
      "rawDislikes": 300,
      "dateCreated": "2025-07-16 12:17:29",
      "collectedAt": "2025-07-16 12:30:01"
    },
    {
      "videoId": "O5zmjhxmE9E",
      "teamName": "MOTIV",
      "rawLikes": 52000,
      "rawDislikes": 300,
      "dateCreated": "2025-07-16 13:28:27",
      "collectedAt": "2025-07-16 13:30:00"
    },
    {
      "videoId": "O5zmjhxmE9E",
      "teamName": "MOTIV",
      "rawLikes": 55200,
      "rawDislikes": 300,
      "dateCreated": "2025-07-16 14:25:24",
      "collectedAt": "2025-07-16 14:30:01"
    },
    {
      "videoId": "O5zmjhxmE9E",
      "teamName": "MOTIV",
      "rawLikes": 57000,
      "rawDislikes": 400,
      "dateCreated": "2025-07-16 15:22:40",
      "collectedAt": "2025-07-16 15:30:01"
    },
    {
      "videoId": "O5zmjhxmE9E",
      "teamName": "MOTIV",
      "rawLikes": 58000,
      "rawDislikes": 500,
      "dateCreated": "2025-07-16 16:24:11",
      "collectedAt": "2025-07-16 16:30:00"
    },
    {
      "videoId": "O5zmjhxmE9E",
      "teamName": "MOTIV",
      "rawLikes": 59600,
      "rawDislikes": 500,
      "dateCreated": "2025-07-16 17:23:36",
      "collectedAt": "2025-07-16 17:30:01"
    },
    {
      "videoId": "O5zmjhxmE9E",
      "teamName": "MOTIV",
      "rawLikes": 61200,
      "rawDislikes": 500,
      "dateCreated": "2025-07-16 18:14:45",
      "collectedAt": "2025-07-16 18:30:00"
    },
    {
      "videoId": "O5zmjhxmE9E",
      "teamName": "MOTIV",
      "rawLikes": 62000,
      "rawDislikes": 500,
      "dateCreated": "2025-07-16 19:23:37",
      "collectedAt": "2025-07-16 19:30:00"
    },
    {
      "videoId": "O5zmjhxmE9E",
      "teamName": "MOTIV",
      "rawLikes": 63600,
      "rawDislikes": 500,
      "dateCreated": "2025-07-16 20:21:41",
      "collectedAt": "2025-07-16 20:30:00"
    },
    {
      "videoId": "O5zmjhxmE9E",
      "teamName": "MOTIV",
      "rawLikes": 66200,
      "rawDislikes": 500,
      "dateCreated": "2025-07-16 21:18:15",
      "collectedAt": "2025-07-16 21:30:00"
    },
    {
      "videoId": "O5zmjhxmE9E",
      "teamName": "MOTIV",
      "rawLikes": 68000,
      "rawDislikes": 500,
      "dateCreated": "2025-07-16 22:19:26",
      "collectedAt": "2025-07-16 22:30:00"
    },
    {
      "videoId": "O5zmjhxmE9E",
      "teamName": "MOTIV",
      "rawLikes": 69400,
      "rawDislikes": 500,
      "dateCreated": "2025-07-16 23:11:37",
      "collectedAt": "2025-07-16 23:30:01"
    }
  ]
}
