{
    "2025-07-05": [
        {
            "videoId": "da68UOXfQ_s",
            "teamName": "AGSQUAD",
            "rawLikes": 248000,
            "rawDislikes": 1800,
            "dateCreated": "2025-07-05 00:16:18",
            "collectedAt": "2025-07-05 00:30:00"
        },
        {
            "videoId": "da68UOXfQ_s",
            "teamName": "AGSQUAD",
            "rawLikes": 249200,
            "rawDislikes": 1800,
            "dateCreated": "2025-07-05 01:27:20",
            "collectedAt": "2025-07-05 01:30:00"
        },
        {
            "videoId": "da68UOXfQ_s",
            "teamName": "AGSQUAD",
            "rawLikes": 250400,
            "rawDislikes": 1800,
            "dateCreated": "2025-07-05 02:25:00",
            "collectedAt": "2025-07-05 02:30:00"
        },
        {
            "videoId": "da68UOXfQ_s",
            "teamName": "AGSQUAD",
            "rawLikes": 251200,
            "rawDislikes": 2000,
            "dateCreated": "2025-07-05 03:20:09",
            "collectedAt": "2025-07-05 03:30:01"
        },
        {
            "videoId": "da68UOXfQ_s",
            "teamName": "AGSQUAD",
            "rawLikes": 251600,
            "rawDislikes": 2000,
            "dateCreated": "2025-07-05 04:22:33",
            "collectedAt": "2025-07-05 04:30:01"
        },
        {
            "videoId": "da68UOXfQ_s",
            "teamName": "AGSQUAD",
            "rawLikes": 252000,
            "rawDislikes": 2000,
            "dateCreated": "2025-07-05 05:24:39",
            "collectedAt": "2025-07-05 05:30:01"
        },
        {
            "videoId": "da68UOXfQ_s",
            "teamName": "AGSQUAD",
            "rawLikes": 252600,
            "rawDislikes": 2000,
            "dateCreated": "2025-07-05 06:27:56",
            "collectedAt": "2025-07-05 06:30:01"
        },
        {
            "videoId": "da68UOXfQ_s",
            "teamName": "AGSQUAD",
            "rawLikes": 252800,
            "rawDislikes": 2000,
            "dateCreated": "2025-07-05 07:29:58",
            "collectedAt": "2025-07-05 07:30:00"
        },
        {
            "videoId": "da68UOXfQ_s",
            "teamName": "AGSQUAD",
            "rawLikes": 253600,
            "rawDislikes": 2000,
            "dateCreated": "2025-07-05 08:28:23",
            "collectedAt": "2025-07-05 08:30:00"
        },
        {
            "videoId": "da68UOXfQ_s",
            "teamName": "AGSQUAD",
            "rawLikes": 254600,
            "rawDislikes": 2000,
            "dateCreated": "2025-07-05 09:24:33",
            "collectedAt": "2025-07-05 09:30:00"
        },
        {
            "videoId": "da68UOXfQ_s",
            "teamName": "AGSQUAD",
            "rawLikes": 255400,
            "rawDislikes": 2000,
            "dateCreated": "2025-07-05 10:23:26",
            "collectedAt": "2025-07-05 10:30:00"
        },
        {
            "videoId": "da68UOXfQ_s",
            "teamName": "AGSQUAD",
            "rawLikes": 255800,
            "rawDislikes": 2000,
            "dateCreated": "2025-07-05 11:22:13",
            "collectedAt": "2025-07-05 11:30:00"
        },
        {
            "videoId": "da68UOXfQ_s",
            "teamName": "AGSQUAD",
            "rawLikes": 256600,
            "rawDislikes": 2000,
            "dateCreated": "2025-07-05 12:19:08",
            "collectedAt": "2025-07-05 12:30:00"
        },
        {
            "videoId": "da68UOXfQ_s",
            "teamName": "AGSQUAD",
            "rawLikes": 257400,
            "rawDislikes": 2000,
            "dateCreated": "2025-07-05 13:28:15",
            "collectedAt": "2025-07-05 13:30:00"
        },
        {
            "videoId": "da68UOXfQ_s",
            "teamName": "AGSQUAD",
            "rawLikes": 258400,
            "rawDislikes": 2000,
            "dateCreated": "2025-07-05 14:13:30",
            "collectedAt": "2025-07-05 14:30:00"
        },
        {
            "videoId": "da68UOXfQ_s",
            "teamName": "AGSQUAD",
            "rawLikes": 259600,
            "rawDislikes": 2000,
            "dateCreated": "2025-07-05 15:29:47",
            "collectedAt": "2025-07-05 15:30:00"
        },
        {
            "videoId": "da68UOXfQ_s",
            "teamName": "AGSQUAD",
            "rawLikes": 261600,
            "rawDislikes": 2000,
            "dateCreated": "2025-07-05 16:26:39",
            "collectedAt": "2025-07-05 16:30:00"
        },
        {
            "videoId": "da68UOXfQ_s",
            "teamName": "AGSQUAD",
            "rawLikes": 262800,
            "rawDislikes": 2000,
            "dateCreated": "2025-07-05 17:26:02",
            "collectedAt": "2025-07-05 17:30:00"
        }
    ],
    "2025-07-04": [
        {
            "videoId": "da68UOXfQ_s",
            "teamName": "AGSQUAD",
            "rawLikes": 221400,
            "rawDislikes": 1400,
            "dateCreated": "2025-07-04 00:29:19",
            "collectedAt": "2025-07-04 00:30:00"
        },
        {
            "videoId": "da68UOXfQ_s",
            "teamName": "AGSQUAD",
            "rawLikes": 223600,
            "rawDislikes": 1500,
            "dateCreated": "2025-07-04 01:21:48",
            "collectedAt": "2025-07-04 01:30:00"
        },
        {
            "videoId": "da68UOXfQ_s",
            "teamName": "AGSQUAD",
            "rawLikes": 225400,
            "rawDislikes": 1500,
            "dateCreated": "2025-07-04 02:18:32",
            "collectedAt": "2025-07-04 02:30:00"
        },
        {
            "videoId": "da68UOXfQ_s",
            "teamName": "AGSQUAD",
            "rawLikes": 226600,
            "rawDislikes": 1500,
            "dateCreated": "2025-07-04 03:29:54",
            "collectedAt": "2025-07-04 03:30:00"
        },
        {
            "videoId": "da68UOXfQ_s",
            "teamName": "AGSQUAD",
            "rawLikes": 227200,
            "rawDislikes": 1500,
            "dateCreated": "2025-07-04 04:09:19",
            "collectedAt": "2025-07-04 04:30:00"
        },
        {
            "videoId": "da68UOXfQ_s",
            "teamName": "AGSQUAD",
            "rawLikes": 228400,
            "rawDislikes": 1500,
            "dateCreated": "2025-07-04 05:27:13",
            "collectedAt": "2025-07-04 05:30:00"
        },
        {
            "videoId": "da68UOXfQ_s",
            "teamName": "AGSQUAD",
            "rawLikes": 228800,
            "rawDislikes": 1600,
            "dateCreated": "2025-07-04 06:24:36",
            "collectedAt": "2025-07-04 06:30:01"
        },
        {
            "videoId": "da68UOXfQ_s",
            "teamName": "AGSQUAD",
            "rawLikes": 228800,
            "rawDislikes": 1600,
            "dateCreated": "2025-07-04 07:24:24",
            "collectedAt": "2025-07-04 07:30:01"
        },
        {
            "videoId": "da68UOXfQ_s",
            "teamName": "AGSQUAD",
            "rawLikes": 230400,
            "rawDislikes": 1600,
            "dateCreated": "2025-07-04 08:17:06",
            "collectedAt": "2025-07-04 08:30:00"
        },
        {
            "videoId": "da68UOXfQ_s",
            "teamName": "AGSQUAD",
            "rawLikes": 231800,
            "rawDislikes": 1600,
            "dateCreated": "2025-07-04 09:13:22",
            "collectedAt": "2025-07-04 09:30:01"
        },
        {
            "videoId": "da68UOXfQ_s",
            "teamName": "AGSQUAD",
            "rawLikes": 232600,
            "rawDislikes": 1600,
            "dateCreated": "2025-07-04 10:27:22",
            "collectedAt": "2025-07-04 10:30:00"
        },
        {
            "videoId": "da68UOXfQ_s",
            "teamName": "AGSQUAD",
            "rawLikes": 232800,
            "rawDislikes": 1600,
            "dateCreated": "2025-07-04 11:19:08",
            "collectedAt": "2025-07-04 11:30:00"
        },
        {
            "videoId": "da68UOXfQ_s",
            "teamName": "AGSQUAD",
            "rawLikes": 234200,
            "rawDislikes": 1600,
            "dateCreated": "2025-07-04 12:29:01",
            "collectedAt": "2025-07-04 12:30:00"
        },
        {
            "videoId": "da68UOXfQ_s",
            "teamName": "AGSQUAD",
            "rawLikes": 235600,
            "rawDislikes": 1600,
            "dateCreated": "2025-07-04 13:24:28",
            "collectedAt": "2025-07-04 13:30:01"
        },
        {
            "videoId": "da68UOXfQ_s",
            "teamName": "AGSQUAD",
            "rawLikes": 236800,
            "rawDislikes": 1600,
            "dateCreated": "2025-07-04 14:23:37",
            "collectedAt": "2025-07-04 14:30:00"
        },
        {
            "videoId": "da68UOXfQ_s",
            "teamName": "AGSQUAD",
            "rawLikes": 237800,
            "rawDislikes": 1600,
            "dateCreated": "2025-07-04 15:29:00",
            "collectedAt": "2025-07-04 15:30:00"
        },
        {
            "videoId": "da68UOXfQ_s",
            "teamName": "AGSQUAD",
            "rawLikes": 238600,
            "rawDislikes": 1700,
            "dateCreated": "2025-07-04 16:20:45",
            "collectedAt": "2025-07-04 16:30:01"
        },
        {
            "videoId": "da68UOXfQ_s",
            "teamName": "AGSQUAD",
            "rawLikes": 238600,
            "rawDislikes": 1700,
            "dateCreated": "2025-07-04 17:17:52",
            "collectedAt": "2025-07-04 17:30:01"
        },
        {
            "videoId": "da68UOXfQ_s",
            "teamName": "AGSQUAD",
            "rawLikes": 239800,
            "rawDislikes": 1800,
            "dateCreated": "2025-07-04 18:19:16",
            "collectedAt": "2025-07-04 18:30:00"
        },
        {
            "videoId": "da68UOXfQ_s",
            "teamName": "AGSQUAD",
            "rawLikes": 240800,
            "rawDislikes": 1800,
            "dateCreated": "2025-07-04 19:24:58",
            "collectedAt": "2025-07-04 19:30:00"
        },
        {
            "videoId": "da68UOXfQ_s",
            "teamName": "AGSQUAD",
            "rawLikes": 242000,
            "rawDislikes": 1800,
            "dateCreated": "2025-07-04 20:18:25",
            "collectedAt": "2025-07-04 20:30:00"
        },
        {
            "videoId": "da68UOXfQ_s",
            "teamName": "AGSQUAD",
            "rawLikes": 243400,
            "rawDislikes": 1800,
            "dateCreated": "2025-07-04 21:26:44",
            "collectedAt": "2025-07-04 21:30:00"
        },
        {
            "videoId": "da68UOXfQ_s",
            "teamName": "AGSQUAD",
            "rawLikes": 244800,
            "rawDislikes": 1800,
            "dateCreated": "2025-07-04 22:20:43",
            "collectedAt": "2025-07-04 22:30:00"
        },
        {
            "videoId": "da68UOXfQ_s",
            "teamName": "AGSQUAD",
            "rawLikes": 246200,
            "rawDislikes": 1800,
            "dateCreated": "2025-07-04 23:29:30",
            "collectedAt": "2025-07-04 23:30:01"
        }
    ],
    "2025-07-03": [
        {
            "videoId": "da68UOXfQ_s",
            "teamName": "AGSQUAD",
            "rawLikes": 179800,
            "rawDislikes": 1100,
            "dateCreated": "2025-07-03 00:20:27",
            "collectedAt": "2025-07-03 00:30:01"
        },
        {
            "videoId": "da68UOXfQ_s",
            "teamName": "AGSQUAD",
            "rawLikes": 183600,
            "rawDislikes": 1200,
            "dateCreated": "2025-07-03 01:26:20",
            "collectedAt": "2025-07-03 01:30:00"
        },
        {
            "videoId": "da68UOXfQ_s",
            "teamName": "AGSQUAD",
            "rawLikes": 187000,
            "rawDislikes": 1200,
            "dateCreated": "2025-07-03 02:17:12",
            "collectedAt": "2025-07-03 02:30:00"
        },
        {
            "videoId": "da68UOXfQ_s",
            "teamName": "AGSQUAD",
            "rawLikes": 189200,
            "rawDislikes": 1200,
            "dateCreated": "2025-07-03 03:26:22",
            "collectedAt": "2025-07-03 03:30:01"
        },
        {
            "videoId": "da68UOXfQ_s",
            "teamName": "AGSQUAD",
            "rawLikes": 190600,
            "rawDislikes": 1200,
            "dateCreated": "2025-07-03 04:21:11",
            "collectedAt": "2025-07-03 04:30:01"
        },
        {
            "videoId": "da68UOXfQ_s",
            "teamName": "AGSQUAD",
            "rawLikes": 191600,
            "rawDislikes": 1200,
            "dateCreated": "2025-07-03 05:11:34",
            "collectedAt": "2025-07-03 05:30:01"
        },
        {
            "videoId": "da68UOXfQ_s",
            "teamName": "AGSQUAD",
            "rawLikes": 192800,
            "rawDislikes": 1200,
            "dateCreated": "2025-07-03 06:16:13",
            "collectedAt": "2025-07-03 06:30:01"
        },
        {
            "videoId": "da68UOXfQ_s",
            "teamName": "AGSQUAD",
            "rawLikes": 193400,
            "rawDislikes": 1200,
            "dateCreated": "2025-07-03 07:24:19",
            "collectedAt": "2025-07-03 07:30:00"
        },
        {
            "videoId": "da68UOXfQ_s",
            "teamName": "AGSQUAD",
            "rawLikes": 194800,
            "rawDislikes": 1200,
            "dateCreated": "2025-07-03 08:15:54",
            "collectedAt": "2025-07-03 08:30:00"
        },
        {
            "videoId": "da68UOXfQ_s",
            "teamName": "AGSQUAD",
            "rawLikes": 195600,
            "rawDislikes": 1200,
            "dateCreated": "2025-07-03 09:26:04",
            "collectedAt": "2025-07-03 09:30:00"
        },
        {
            "videoId": "da68UOXfQ_s",
            "teamName": "AGSQUAD",
            "rawLikes": 197000,
            "rawDislikes": 1300,
            "dateCreated": "2025-07-03 10:16:46",
            "collectedAt": "2025-07-03 10:30:00"
        },
        {
            "videoId": "da68UOXfQ_s",
            "teamName": "AGSQUAD",
            "rawLikes": 198600,
            "rawDislikes": 1300,
            "dateCreated": "2025-07-03 11:26:24",
            "collectedAt": "2025-07-03 11:30:01"
        },
        {
            "videoId": "da68UOXfQ_s",
            "teamName": "AGSQUAD",
            "rawLikes": 201600,
            "rawDislikes": 1300,
            "dateCreated": "2025-07-03 12:15:31",
            "collectedAt": "2025-07-03 12:30:00"
        },
        {
            "videoId": "da68UOXfQ_s",
            "teamName": "AGSQUAD",
            "rawLikes": 203200,
            "rawDislikes": 1300,
            "dateCreated": "2025-07-03 13:23:16",
            "collectedAt": "2025-07-03 13:30:00"
        },
        {
            "videoId": "da68UOXfQ_s",
            "teamName": "AGSQUAD",
            "rawLikes": 204400,
            "rawDislikes": 1300,
            "dateCreated": "2025-07-03 14:14:42",
            "collectedAt": "2025-07-03 14:30:00"
        },
        {
            "videoId": "da68UOXfQ_s",
            "teamName": "AGSQUAD",
            "rawLikes": 205800,
            "rawDislikes": 1300,
            "dateCreated": "2025-07-03 15:19:30",
            "collectedAt": "2025-07-03 15:30:00"
        },
        {
            "videoId": "da68UOXfQ_s",
            "teamName": "AGSQUAD",
            "rawLikes": 207400,
            "rawDislikes": 1300,
            "dateCreated": "2025-07-03 16:16:14",
            "collectedAt": "2025-07-03 16:30:00"
        },
        {
            "videoId": "da68UOXfQ_s",
            "teamName": "AGSQUAD",
            "rawLikes": 209600,
            "rawDislikes": 1300,
            "dateCreated": "2025-07-03 17:29:54",
            "collectedAt": "2025-07-03 17:30:00"
        },
        {
            "videoId": "da68UOXfQ_s",
            "teamName": "AGSQUAD",
            "rawLikes": 210400,
            "rawDislikes": 1300,
            "dateCreated": "2025-07-03 18:24:38",
            "collectedAt": "2025-07-03 18:30:00"
        },
        {
            "videoId": "da68UOXfQ_s",
            "teamName": "AGSQUAD",
            "rawLikes": 211800,
            "rawDislikes": 1300,
            "dateCreated": "2025-07-03 19:14:04",
            "collectedAt": "2025-07-03 19:30:00"
        },
        {
            "videoId": "da68UOXfQ_s",
            "teamName": "AGSQUAD",
            "rawLikes": 212600,
            "rawDislikes": 1300,
            "dateCreated": "2025-07-03 20:23:50",
            "collectedAt": "2025-07-03 20:30:00"
        },
        {
            "videoId": "da68UOXfQ_s",
            "teamName": "AGSQUAD",
            "rawLikes": 215800,
            "rawDislikes": 1300,
            "dateCreated": "2025-07-03 21:28:26",
            "collectedAt": "2025-07-03 21:30:00"
        },
        {
            "videoId": "da68UOXfQ_s",
            "teamName": "AGSQUAD",
            "rawLikes": 217600,
            "rawDislikes": 1400,
            "dateCreated": "2025-07-03 22:17:40",
            "collectedAt": "2025-07-03 22:30:00"
        },
        {
            "videoId": "da68UOXfQ_s",
            "teamName": "AGSQUAD",
            "rawLikes": 219400,
            "rawDislikes": 1400,
            "dateCreated": "2025-07-03 23:26:19",
            "collectedAt": "2025-07-03 23:30:00"
        }
    ],
    "2025-07-02": [
        {
            "videoId": "da68UOXfQ_s",
            "teamName": "AGSQUAD",
            "rawLikes": 9200,
            "rawDislikes": 0,
            "dateCreated": "2025-07-02 01:24:49",
            "collectedAt": "2025-07-02 01:30:00"
        },
        {
            "videoId": "da68UOXfQ_s",
            "teamName": "AGSQUAD",
            "rawLikes": 48000,
            "rawDislikes": 100,
            "dateCreated": "2025-07-02 02:23:48",
            "collectedAt": "2025-07-02 02:30:00"
        },
        {
            "videoId": "da68UOXfQ_s",
            "teamName": "AGSQUAD",
            "rawLikes": 59200,
            "rawDislikes": 200,
            "dateCreated": "2025-07-02 03:25:48",
            "collectedAt": "2025-07-02 03:30:00"
        },
        {
            "videoId": "da68UOXfQ_s",
            "teamName": "AGSQUAD",
            "rawLikes": 67200,
            "rawDislikes": 200,
            "dateCreated": "2025-07-02 04:26:06",
            "collectedAt": "2025-07-02 04:30:00"
        },
        {
            "videoId": "da68UOXfQ_s",
            "teamName": "AGSQUAD",
            "rawLikes": 70400,
            "rawDislikes": 200,
            "dateCreated": "2025-07-02 05:29:49",
            "collectedAt": "2025-07-02 05:30:00"
        },
        {
            "videoId": "da68UOXfQ_s",
            "teamName": "AGSQUAD",
            "rawLikes": 74400,
            "rawDislikes": 200,
            "dateCreated": "2025-07-02 06:26:00",
            "collectedAt": "2025-07-02 06:30:00"
        },
        {
            "videoId": "da68UOXfQ_s",
            "teamName": "AGSQUAD",
            "rawLikes": 80000,
            "rawDislikes": 400,
            "dateCreated": "2025-07-02 07:20:42",
            "collectedAt": "2025-07-02 07:30:00"
        },
        {
            "videoId": "da68UOXfQ_s",
            "teamName": "AGSQUAD",
            "rawLikes": 90200,
            "rawDislikes": 400,
            "dateCreated": "2025-07-02 08:23:28",
            "collectedAt": "2025-07-02 08:30:00"
        },
        {
            "videoId": "da68UOXfQ_s",
            "teamName": "AGSQUAD",
            "rawLikes": 98200,
            "rawDislikes": 500,
            "dateCreated": "2025-07-02 09:17:10",
            "collectedAt": "2025-07-02 09:30:00"
        },
        {
            "videoId": "da68UOXfQ_s",
            "teamName": "AGSQUAD",
            "rawLikes": 104800,
            "rawDislikes": 600,
            "dateCreated": "2025-07-02 10:21:32",
            "collectedAt": "2025-07-02 10:30:00"
        },
        {
            "videoId": "da68UOXfQ_s",
            "teamName": "AGSQUAD",
            "rawLikes": 110800,
            "rawDislikes": 600,
            "dateCreated": "2025-07-02 11:25:09",
            "collectedAt": "2025-07-02 11:30:00"
        },
        {
            "videoId": "da68UOXfQ_s",
            "teamName": "AGSQUAD",
            "rawLikes": 119600,
            "rawDislikes": 600,
            "dateCreated": "2025-07-02 12:12:01",
            "collectedAt": "2025-07-02 12:30:00"
        },
        {
            "videoId": "da68UOXfQ_s",
            "teamName": "AGSQUAD",
            "rawLikes": 128000,
            "rawDislikes": 800,
            "dateCreated": "2025-07-02 13:17:37",
            "collectedAt": "2025-07-02 13:30:00"
        },
        {
            "videoId": "da68UOXfQ_s",
            "teamName": "AGSQUAD",
            "rawLikes": 134400,
            "rawDislikes": 800,
            "dateCreated": "2025-07-02 14:23:17",
            "collectedAt": "2025-07-02 14:30:00"
        },
        {
            "videoId": "da68UOXfQ_s",
            "teamName": "AGSQUAD",
            "rawLikes": 140200,
            "rawDislikes": 900,
            "dateCreated": "2025-07-02 15:12:26",
            "collectedAt": "2025-07-02 15:30:00"
        },
        {
            "videoId": "da68UOXfQ_s",
            "teamName": "AGSQUAD",
            "rawLikes": 142400,
            "rawDislikes": 900,
            "dateCreated": "2025-07-02 16:18:43",
            "collectedAt": "2025-07-02 16:30:00"
        },
        {
            "videoId": "da68UOXfQ_s",
            "teamName": "AGSQUAD",
            "rawLikes": 147200,
            "rawDislikes": 900,
            "dateCreated": "2025-07-02 17:21:17",
            "collectedAt": "2025-07-02 17:30:00"
        },
        {
            "videoId": "da68UOXfQ_s",
            "teamName": "AGSQUAD",
            "rawLikes": 151400,
            "rawDislikes": 1000,
            "dateCreated": "2025-07-02 18:24:37",
            "collectedAt": "2025-07-02 18:30:00"
        },
        {
            "videoId": "da68UOXfQ_s",
            "teamName": "AGSQUAD",
            "rawLikes": 155400,
            "rawDislikes": 1000,
            "dateCreated": "2025-07-02 19:13:45",
            "collectedAt": "2025-07-02 19:30:00"
        },
        {
            "videoId": "da68UOXfQ_s",
            "teamName": "AGSQUAD",
            "rawLikes": 159800,
            "rawDislikes": 1000,
            "dateCreated": "2025-07-02 20:19:02",
            "collectedAt": "2025-07-02 20:30:00"
        },
        {
            "videoId": "da68UOXfQ_s",
            "teamName": "AGSQUAD",
            "rawLikes": 164000,
            "rawDislikes": 1000,
            "dateCreated": "2025-07-02 21:25:24",
            "collectedAt": "2025-07-02 21:30:00"
        },
        {
            "videoId": "da68UOXfQ_s",
            "teamName": "AGSQUAD",
            "rawLikes": 169600,
            "rawDislikes": 1000,
            "dateCreated": "2025-07-02 22:27:44",
            "collectedAt": "2025-07-02 22:30:00"
        },
        {
            "videoId": "da68UOXfQ_s",
            "teamName": "AGSQUAD",
            "rawLikes": 174800,
            "rawDislikes": 1100,
            "dateCreated": "2025-07-02 23:15:13",
            "collectedAt": "2025-07-02 23:30:00"
        }
    ]
}